heiko/__init__.py
heiko/items.py
heiko/maassimpleconfig.py
heiko/menu.py
heiko/migrate.py
heiko/nfc.py
heiko/service.py
heiko/users.py
heiko/utils.py
heiko/voice.py
swagger_client/__init__.py
swagger_client/api_client.py
swagger_client/configuration.py
swagger_client/rest.py
swagger_client/api/__init__.py
swagger_client/api/auth_api.py
swagger_client/api/items_api.py
swagger_client/api/service_api.py
swagger_client/api/users_api.py
swagger_client/models/__init__.py
swagger_client/models/auth_success.py
swagger_client/models/error.py
swagger_client/models/item.py
swagger_client/models/item_stats.py
swagger_client/models/service_stats.py
swagger_client/models/service_stats_items.py
swagger_client/models/service_stats_items_cost.py
swagger_client/models/service_stats_users.py
swagger_client/models/service_stats_users_credits.py
swagger_client/models/transferred_credits.py
swagger_client/models/user.py
swagger_client/models/user_stats.py
test/__init__.py
test/test_auth_api.py
test/test_auth_success.py
test/test_error.py
test/test_item.py
test/test_item_stats.py
test/test_items_api.py
test/test_service_api.py
test/test_service_stats.py
test/test_service_stats_items.py
test/test_service_stats_items_cost.py
test/test_service_stats_users.py
test/test_service_stats_users_credits.py
test/test_transferred_credits.py
test/test_user.py
test/test_user_stats.py
test/test_users_api.py
heiko-4.6.0.dist-info/LICENSE
heiko-4.6.0.dist-info/METADATA
heiko-4.6.0.dist-info/WHEEL
heiko-4.6.0.dist-info/entry_points.txt
heiko-4.6.0.dist-info/top_level.txt
heiko-4.6.0.dist-info/zip-safe
heiko-4.6.0.dist-info/RECORD
