Metadata-Version: 2.1
Name: heiko
Version: 4.6.0
Summary: Heiko is a frontend for MaaS
Home-page: https://github.com/k4cg/heiko
Author: K4CG
Author-email: info@k4cg.org
License: MIT
Keywords: mate matomat beer drinks accounting
Platform: UNKNOWN
Classifier: Development Status :: 4 - Beta
Classifier: Topic :: Utilities
Classifier: Topic :: Terminals
Classifier: License :: OSI Approved :: MIT License
Classifier: Programming Language :: Python :: 3.5
Classifier: Programming Language :: Python :: 3.6
Classifier: Programming Language :: Python :: 3.7
Requires-Dist: certifi (>=14.05.14)
Requires-Dist: six (>=1.10)
Requires-Dist: python-dateutil (>=2.5.3)
Requires-Dist: setuptools (>=21.0.0)
Requires-Dist: urllib3 (>=1.15.1)
Requires-Dist: sty
Requires-Dist: tabulate
Requires-Dist: pyyaml
Requires-Dist: pygame
Requires-Dist: watson-developer-cloud
Provides-Extra: dev
Requires-Dist: bumpversion ; extra == 'dev'
Requires-Dist: gitchangelog ; extra == 'dev'
Requires-Dist: twine ; extra == 'dev'
Requires-Dist: setuptools ; extra == 'dev'
